{
    "52029779": "https://preview-sjh.baidu.com/site/pp.jxwapkgh.cn/347fa169-f3b6-4ff9-8bfb-bb61c903bc04?time=1594967237488&showpageinpc=0",
    "52091001": "https://preview-sjh.baidu.com/site/3.bugg14.com/6b7f8dbd-8034-4a6a-8e27-bd68cb9484e3?time=1594967386519&showpageinpc=0",
    "51743380": "https://preview-sjh.baidu.com/site/3.bugg14.com/8c53ae3b-0b72-4805-b430-4a76a3b5cbe9?time=1594967412993&showpageinpc=0",
    "51686057": "https://preview-sjh.baidu.com/site/3.bugg14.com/99cf3287-eafc-4d0d-ad32-44bc37e1b7d5?time=1594967433135&showpageinpc=0",
    "51242730": "https://preview-sjh.baidu.com/site/3.bugg14.com/7fe11a57-aaab-4686-aeeb-ded88d304ee3?time=1594967486456&showpageinpc=0",
    "51483472": "https://preview-sjh.baidu.com/site/3.bugg14.com/fa2eca69-6889-4a10-a385-d481b8cb26a8?time=1594967451980&showpageinpc=0"
}